teams_card/AdaptiveCard.py
teams_card/BaseElement.py
teams_card/TextBlock.py
teams_card/__init__.py
teams_card-0.0.2.dist-info/LICENSE
teams_card-0.0.2.dist-info/METADATA
teams_card-0.0.2.dist-info/WHEEL
teams_card-0.0.2.dist-info/top_level.txt
teams_card-0.0.2.dist-info/RECORD
