Metadata-Version: 2.1
Name: teams-card
Version: 0.0.2
Summary: A mini utility to create cards for chatbot usage
Home-page: https://github.com/nischkar/teams-card
Author: nischkar
Author-email: contact@nischkar.com
Project-URL: Bug Tracker, https://github.com/nischkar/teams-card
Classifier: Programming Language :: Python :: 3
Classifier: License :: OSI Approved :: MIT License
Classifier: Operating System :: OS Independent
Requires-Python: >=3.6
License-File: LICENSE
